setup.py
gaminator/__init__.py
gaminator/canvas.py
gaminator/collisions.py
gaminator/color.py
gaminator/constants.py
gaminator/events.py
gaminator/exceptions.py
gaminator/game.py
gaminator/interactive.py
gaminator/picture.py
gaminator/picture_thing.py
gaminator/thing.py
gaminator/thing_type.py
gaminator/window.py
gaminator/world.py
gaminator.egg-info/PKG-INFO
gaminator.egg-info/SOURCES.txt
gaminator.egg-info/dependency_links.txt
gaminator.egg-info/top_level.txt
gaminator/starter/__init__.py
gaminator/starter/__main__.py
gaminator/starter/shapes.py
gaminator_sk/__init__.py
gaminator_sk/canvas.py
gaminator_sk/collisions.py
gaminator_sk/color.py
gaminator_sk/constants.py
gaminator_sk/events.py
gaminator_sk/exceptions.py
gaminator_sk/game.py
gaminator_sk/interactive.py
gaminator_sk/picture.py
gaminator_sk/picture_thing.py
gaminator_sk/thing.py
gaminator_sk/thing_type.py
gaminator_sk/window.py
gaminator_sk/world.py
gaminator_sk/starter/__init__.py
gaminator_sk/starter/__main__.py
gaminator_sk/starter/shapes.py