Metadata-Version: 1.1
Name: gaminator
Version: 0.1.3
Summary: A library for easy and fast development of simple games.
